omniblack/sphinx_type_role/__init__.py
omniblack/sphinx_type_role/resolve_type.py
omniblack.sphinx_type_role-0.0.2.dist-info/LICENSE.txt
omniblack.sphinx_type_role-0.0.2.dist-info/METADATA
omniblack.sphinx_type_role-0.0.2.dist-info/WHEEL
omniblack.sphinx_type_role-0.0.2.dist-info/top_level.txt
omniblack.sphinx_type_role-0.0.2.dist-info/RECORD
