Metadata-Version: 2.1
Name: omniblack.sphinx-type-role
Version: 0.0.2
Author-email: Terry Patterson <Terryp@wegrok.net>
License: 
Project-URL: Homepage, https://gitlab.com/terryp/terry/-/tree/next/lib/sphinx_type_role
Project-URL: Repository, https://gitlab.com/terryp/terry.git
License-File: LICENSE.txt
Requires-Dist: docutils
Requires-Dist: sphinx
